boilerplate_x/__init__.py
boilerplate_x/chain.py
boilerplate_x/cli.py
boilerplate_x/constants.py
boilerplate_x/generator.py
boilerplate_x/github.py
boilerplate_x/schemas.py
boilerplate_x-0.2.8.dist-info/LICENSE
boilerplate_x-0.2.8.dist-info/METADATA
boilerplate_x-0.2.8.dist-info/WHEEL
boilerplate_x-0.2.8.dist-info/entry_points.txt
boilerplate_x-0.2.8.dist-info/RECORD
