Metadata-Version: 2.1
Name: boilerplate-x
Version: 0.2.8
Summary: Create project boilerplate for any programming language in minutes, with just an idea.
Home-page: https://www.github.com/ajndkr/boilerplate-x
License: MIT
Author: Ajinkya Indulkar
Author-email: 26824103+ajndkr@users.noreply.github.com
Requires-Python: >=3.9,<4.0
Classifier: License :: OSI Approved :: MIT License
Classifier: Programming Language :: Python :: 3
Classifier: Programming Language :: Python :: 3.9
Classifier: Programming Language :: Python :: 3.10
Classifier: Programming Language :: Python :: 3.11
Requires-Dist: click (>=8.1.3,<9.0.0)
Requires-Dist: gitpython (>=3.1.31,<4.0.0)
Requires-Dist: langchain (>=0.0.123,<0.0.124)
Requires-Dist: openai (>=0.27.2,<0.28.0)
Requires-Dist: pygithub (>=1.58.1,<2.0.0)
Requires-Dist: rich (>=13.3.3,<14.0.0)
Requires-Dist: tiktoken (>=0.3.2,<0.4.0)
Project-URL: Repository, https://www.github.com/ajndkr/boilerplate-x
